{
  "id": "python",
  "title": "Python",
  "nodes": [
    { "id": "data-types",            "type": "lesson",    "title": "Data Types",                  "x": 280, "y": 80   },
    { "id": "variables",             "type": "lesson",    "title": "Variables",                   "x": 480, "y": 80   },
    { "id": "terminal-io",           "type": "lesson",    "title": "Terminal I/O",                "x": 480, "y": 210  },
    { "id": "boolean-logic",         "type": "lesson",    "title": "Boolean Logic",               "x": 280, "y": 210  },
    { "id": "conditionals",          "type": "lesson",    "title": "Conditionals",                "x": 280, "y": 340  },
    { "id": "strings",               "type": "lesson",    "title": "Strings",                     "x": 480, "y": 340  },
    { "id": "ws1-challenge",         "type": "challenge", "title": "Challenge: Worksheet 1",      "x": 380, "y": 470  },
    { "id": "lists",                 "type": "lesson",    "title": "Lists",                       "x": 280, "y": 600  },
    { "id": "loops",                 "type": "lesson",    "title": "Loops",                       "x": 480, "y": 600  },
    { "id": "functions",             "type": "lesson",    "title": "Functions",                   "x": 480, "y": 730  },
    { "id": "nonetype",              "type": "lesson",    "title": "NoneType",                    "x": 280, "y": 730  },
    { "id": "errors",                "type": "lesson",    "title": "Errors",                      "x": 280, "y": 860  },
    { "id": "stacks",                "type": "lesson",    "title": "Stacks",                      "x": 480, "y": 860  },
    { "id": "ws2-challenge",         "type": "challenge", "title": "Challenge: Worksheet 2",      "x": 380, "y": 990  },
    { "id": "tuples",                "type": "lesson",    "title": "Tuples",                      "x": 280, "y": 1120 },
    { "id": "sets",                  "type": "lesson",    "title": "Sets",                        "x": 480, "y": 1120 },
    { "id": "dictionaries",          "type": "lesson",    "title": "Dictionaries",                "x": 480, "y": 1250 },
    { "id": "tuples-in-lists",       "type": "lesson",    "title": "Tuples in Lists",             "x": 280, "y": 1250 },
    { "id": "merging-dictionaries",  "type": "lesson",    "title": "Merging Dictionaries",        "x": 280, "y": 1380 },
    { "id": "advanced-strings",      "type": "lesson",    "title": "Advanced Strings",            "x": 480, "y": 1380 },
    { "id": "string-formatting",     "type": "lesson",    "title": "String Formatting",           "x": 480, "y": 1510 },
    { "id": "list-comprehension",    "type": "lesson",    "title": "List Comprehensions",         "x": 280, "y": 1510 },
    { "id": "set-comprehension",     "type": "lesson",    "title": "Set Comprehensions",          "x": 280, "y": 1640 },
    { "id": "dict-comprehension",    "type": "lesson",    "title": "Dictionary Comprehensions",   "x": 480, "y": 1640 },
    { "id": "ws3-challenge",         "type": "challenge", "title": "Challenge: Worksheet 3",      "x": 380, "y": 1770 },
    { "id": "comprehensions",        "type": "lesson",    "title": "Comprehensions Refresher",    "x": 280, "y": 1900 },
    { "id": "functions-in-depth",    "type": "lesson",    "title": "Functions in Depth",          "x": 480, "y": 1900 },
    { "id": "lambda",                "type": "lesson",    "title": "Lambda Functions",            "x": 480, "y": 2030 },
    { "id": "files",                 "type": "lesson",    "title": "Working with Files",          "x": 280, "y": 2030 },
    { "id": "classes",               "type": "lesson",    "title": "Classes",                     "x": 280, "y": 2160 },
    { "id": "ws4-challenge",         "type": "challenge", "title": "Challenge: Worksheet 4",      "x": 380, "y": 2290 }
  ],
  "edges": [
    { "from": "data-types",           "to": "variables"            },
    { "from": "variables",            "to": "terminal-io"          },
    { "from": "terminal-io",          "to": "boolean-logic"        },
    { "from": "boolean-logic",        "to": "conditionals"         },
    { "from": "conditionals",         "to": "strings"              },
    { "from": "strings",              "to": "ws1-challenge"        },
    { "from": "ws1-challenge",        "to": "lists"                },
    { "from": "lists",                "to": "loops"                },
    { "from": "loops",                "to": "functions"            },
    { "from": "functions",            "to": "nonetype"             },
    { "from": "nonetype",             "to": "errors"               },
    { "from": "errors",               "to": "stacks"               },
    { "from": "stacks",               "to": "ws2-challenge"        },
    { "from": "ws2-challenge",        "to": "tuples"               },
    { "from": "tuples",               "to": "sets"                 },
    { "from": "sets",                 "to": "dictionaries"         },
    { "from": "dictionaries",         "to": "tuples-in-lists"      },
    { "from": "tuples-in-lists",      "to": "merging-dictionaries" },
    { "from": "merging-dictionaries", "to": "advanced-strings"     },
    { "from": "advanced-strings",     "to": "string-formatting"    },
    { "from": "string-formatting",    "to": "list-comprehension"   },
    { "from": "list-comprehension",   "to": "set-comprehension"    },
    { "from": "set-comprehension",    "to": "dict-comprehension"   },
    { "from": "dict-comprehension",   "to": "ws3-challenge"        },
    { "from": "ws3-challenge",        "to": "comprehensions"       },
    { "from": "comprehensions",       "to": "functions-in-depth"   },
    { "from": "functions-in-depth",   "to": "lambda"               },
    { "from": "lambda",               "to": "files"                },
    { "from": "files",                "to": "classes"              },
    { "from": "classes",              "to": "ws4-challenge"        }
  ]
}
